yapsched/__init__.py
yapsched/events.py
yapsched/executor.py
yapsched/job.py
yapsched/scheduler.py
yapsched/triggers.py
yapsched/util.py
yapsched/jobstores/__init__.py
yapsched/jobstores/memory.py
yapsched/jobstores/sqlalchemy.py
yapsched-0.4.0.dist-info/METADATA
yapsched-0.4.0.dist-info/WHEEL
yapsched-0.4.0.dist-info/top_level.txt
yapsched-0.4.0.dist-info/RECORD
